{
  "parent": "minecraft:recipes/root",
  "rewards": {
    "recipes": [
      "tothemoon:crafting/redstone_steel_chestplate_from_redstone_steel_alloy"
    ]
  },
  "criteria": {
    "tick": {
      "trigger": "minecraft:tick",
      "conditions": {}
    },
    "has_the_recipe": {
      "trigger": "minecraft:recipe_unlocked",
      "conditions": {
        "recipe": "tothemoon:crafting/redstone_steel_chestplate_from_redstone_steel_alloy"
      }
    }
  },
  "requirements": [
    [
      "tick",
      "has_the_recipe"
    ]
  ]
}