{
  "parent": "minecraft:recipes/root",
  "rewards": {
    "recipes": [
      "tothemoon:alloying/steel_ingot"
    ]
  },
  "criteria": {
    "has_barrier_and_barrier": {
      "trigger": "minecraft:inventory_changed",
      "conditions": {
        "items": [
          {
            "items": [
              "minecraft:barrier"
            ]
          },
          {
            "items": [
              "minecraft:barrier"
            ]
          }
        ]
      }
    },
    "tick": {
      "trigger": "minecraft:tick",
      "conditions": {}
    },
    "unlock_recipe": {
      "trigger": "minecraft:recipe_unlocked",
      "conditions": {
        "recipe": "tothemoon:alloying/steel_ingot"
      }
    }
  },
  "requirements": [
    [
      "has_barrier_and_barrier"
    ],
    [
      "tick"
    ],
    [
      "unlock_recipe"
    ]
  ]
}